pytest_quarantine/__init__.py
pytest_quarantine/plugin.py
pytest_quarantine-2.0.0.dist-info/LICENSE
pytest_quarantine-2.0.0.dist-info/METADATA
pytest_quarantine-2.0.0.dist-info/WHEEL
pytest_quarantine-2.0.0.dist-info/entry_points.txt
pytest_quarantine-2.0.0.dist-info/top_level.txt
pytest_quarantine-2.0.0.dist-info/RECORD
